badger_proxy/__init__.py
badger_proxy/badger.py
badger_proxy/cli.py
badger_proxy/proxy/__init__.py
badger_proxy/proxy/handler.py
badger_proxy/proxy/proxy.py
badger_proxy/utilities.py
badger_proxy-0.1.9.dist-info/entry_points.txt
badger_proxy-0.1.9.dist-info/LICENSE
badger_proxy-0.1.9.dist-info/WHEEL
badger_proxy-0.1.9.dist-info/METADATA
badger_proxy-0.1.9.dist-info/RECORD
